{
  "bot_states": [
    {
      "ID": 0,
      "direction": -3.4929891235135102,
      "state": {
        "states": "SEARCHING"
      },
      "x_position": -2755.5877609753688,
      "y_position": -1401.9328415436551
    },
    {
      "ID": 1,
      "direction": 4.3019138090005828,
      "state": {
        "states": "SLEEPING"
      },
      "x_position": -74.895909432596298,
      "y_position": -12.751229784366785
    },
    {
      "ID": 2,
      "direction": -8.4193576908656862,
      "state": {
        "states": "SEARCHING"
      },
      "x_position": -59.661721487097886,
      "y_position": -1891.5456835720477
    },
    {
      "ID": 3,
      "direction": 1.0629625633672359,
      "state": {
        "states": "SLEEPING"
      },
      "x_position": -44.636488973048472,
      "y_position": -71.07815461143548
    },
    {
      "ID": 4,
      "direction": 5.4104693943303506,
      "state": {
        "states": "SEARCHING"
      },
      "x_position": -710.61337447478695,
      "y_position": 652.12483534492492
    },
    {
      "ID": 5,
      "direction": 5.939771500336855,
      "state": {
        "states": "SEARCHING"
      },
      "x_position": 1194.9057684313841,
      "y_position": -88.739127395347026
    },
    {
      "ID": 6,
      "direction": -8.1938234793857134,
      "state": {
        "states": "SEARCHING"
      },
      "x_position": -102.47009047662003,
      "y_position": 1541.631563435712
    },
    {
      "ID": 7,
      "direction": 2.9754568799858871,
      "state": {
        "states": "SEARCHING"
      },
      "x_position": -2530.3235255581653,
      "y_position": -1137.8948943146963
    },
    {
      "ID": 8,
      "direction": 0.39768845158314953,
      "state": {
        "states": "SLEEPING"
      },
      "x_position": -36.240137921723587,
      "y_position": -36.930134762299495
    },
    {
      "ID": 9,
      "direction": 7.4696239899039574,
      "state": {
        "states": "SEARCHING"
      },
      "x_position": -428.761054674067,
      "y_position": 564.0025144260569
    },
    {
      "ID": 10,
      "direction": 2.0880103425329994,
      "state": {
        "states": "CONVERGING"
      },
      "x_position": 11092.537327343662,
      "y_position": -2002.2884707504102
    },
    {
      "ID": 11,
      "direction": 10.288267515283657,
      "state": {
        "states": "SLEEPING"
      },
      "x_position": 1.7530920895802033,
      "y_position": -118.39056334236717
    },
    {
      "ID": 12,
      "direction": 7.4902606615392209,
      "state": {
        "states": "SLEEPING"
      },
      "x_position": -126.21286410855171,
      "y_position": -81.980325359620693
    },
    {
      "ID": 13,
      "direction": 5.4712304140012282,
      "state": {
        "states": "SLEEPING"
      },
      "x_position": -96.263131715539288,
      "y_position": -113.55083026496715
    },
    {
      "ID": 14,
      "direction": 13.725815865970596,
      "state": {
        "states": "SLEEPING"
      },
      "x_position": -163.09483003307042,
      "y_position": -116.79604776700219
    },
    {
      "ID": 15,
      "direction": 7.8944304448211255,
      "state": {
        "states": "SEARCHING"
      },
      "x_position": 1394.8180928810179,
      "y_position": -1094.3904368051767
    },
    {
      "ID": 16,
      "direction": -5.9096399978514125,
      "state": {
        "states": "SLEEPING"
      },
      "x_position": -98.747734282756625,
      "y_position": -147.87566510239293
    },
    {
      "ID": 17,
      "direction": 0.18342812439422676,
      "state": {
        "states": "SLEEPING"
      },
      "x_position": -63.241270833259748,
      "y_position": -141.12903180120486
    },
    {
      "ID": 18,
      "direction": -2.9453754657999012,
      "state": {
        "states": "SEARCHING"
      },
      "x_position": 1266.1553860841825,
      "y_position": 1183.3949899903855
    },
    {
      "ID": 19,
      "direction": 22.800153658563442,
      "state": {
        "states": "SEARCHING"
      },
      "x_position": 1189.813665034321,
      "y_position": -1356.500956569957
    },
    {
      "ID": 20,
      "direction": 0.57711981291455638,
      "state": {
        "states": "SLEEPING"
      },
      "x_position": -91.309465450624998,
      "y_position": -79.401053720310244
    },
    {
      "ID": 21,
      "direction": 6.2570206236442294,
      "state": {
        "states": "SEARCHING"
      },
      "x_position": -841.25335467943046,
      "y_position": 748.45111889987402
    },
    {
      "ID": 22,
      "direction": -7.305800062294602,
      "state": {
        "states": "SEARCHING"
      },
      "x_position": -1083.3420652744171,
      "y_position": 1903.8139995499755
    },
    {
      "ID": 23,
      "direction": -9.2536170209758417,
      "state": {
        "states": "SEARCHING"
      },
      "x_position": 2345.82389916802,
      "y_position": -418.42988045536151
    },
    {
      "ID": 24,
      "direction": 10.946938279678577,
      "state": {
        "states": "SEARCHING"
      },
      "x_position": -1350.6204672326139,
      "y_position": 1374.315736396828
    },
    {
      "ID": 25,
      "direction": -7.394232084848106,
      "state": {
        "states": "SEARCHING"
      },
      "x_position": 204.21468856015611,
      "y_position": 975.67403701988133
    },
    {
      "ID": 26,
      "direction": 1.8865944922560556,
      "state": {
        "states": "SLEEPING"
      },
      "x_position": -128.58224079769118,
      "y_position": -126.18925459041229
    },
    {
      "ID": 27,
      "direction": 10.14054841185294,
      "state": {
        "states": "SEARCHING"
      },
      "x_position": -854.42531665211618,
      "y_position": 1319.6579876561259
    },
    {
      "ID": 28,
      "direction": 14.388540225780359,
      "state": {
        "states": "SEARCHING"
      },
      "x_position": 530.9830886240502,
      "y_position": 3192.3824982948854
    },
    {
      "ID": 29,
      "direction": 0.103877463325875,
      "state": {
        "states": "SEARCHING"
      },
      "x_position": -1091.4252110945654,
      "y_position": -8.4750992091986372
    },
    {
      "ID": 30,
      "direction": 5.7480120827734638,
      "state": {
        "states": "SLEEPING"
      },
      "x_position": -39.35335507448567,
      "y_position": -199.4388025390634
    },
    {
      "ID": 31,
      "direction": 6.7733508838087539,
      "state": {
        "states": "SEARCHING"
      },
      "x_position": 1826.1185274397631,
      "y_position": 886.05768779596519
    },
    {
      "ID": 32,
      "direction": -4.8133387558226683,
      "state": {
        "states": "SEARCHING"
      },
      "x_position": -1911.3825238112343,
      "y_position": 387.87618176451809
    },
    {
      "ID": 33,
      "direction": 8.1750849355708635,
      "state": {
        "states": "SEARCHING"
      },
      "x_position": 682.09395261548161,
      "y_position": -1568.1206551511896
    },
    {
      "ID": 34,
      "direction": 2.0663528635668618,
      "state": {
        "states": "CONVERGING"
      },
      "x_position": 11128.658823407026,
      "y_position": -2067.6716896735024
    },
    {
      "ID": 35,
      "direction": -7.3073554532461911,
      "state": {
        "states": "SEARCHING"
      },
      "x_position": 368.59305346187273,
      "y_position": 2116.2489914728612
    },
    {
      "ID": 36,
      "direction": 6.4158285597709863,
      "state": {
        "states": "SEARCHING"
      },
      "x_position": 890.39961676024734,
      "y_position": -531.01203152380515
    },
    {
      "ID": 37,
      "direction": 14.285928009872535,
      "state": {
        "states": "SEARCHING"
      },
      "x_position": -830.19897414873572,
      "y_position": 385.20291953099593
    },
    {
      "ID": 38,
      "direction": 10.499394257057522,
      "state": {
        "states": "SEARCHING"
      },
      "x_position": -735.89425367024012,
      "y_position": 1150.9898805939349
    },
    {
      "ID": 39,
      "direction": 4.1756743342693783,
      "state": {
        "states": "SEARCHING"
      },
      "x_position": -3094.1870012583845,
      "y_position": -3160.8798575433893
    },
    {
      "ID": 40,
      "direction": 3.8343821455021962,
      "state": {
        "states": "SLEEPING"
      },
      "x_position": -74.253826934424012,
      "y_position": -48.987411060993082
    },
    {
      "ID": 41,
      "direction": 5.2831356741706852,
      "state": {
        "states": "SLEEPING"
      },
      "x_position": -28.026033589515144,
      "y_position": -100.86165286624031
    },
    {
      "ID": 42,
      "direction": 4.8489645152264211,
      "state": {
        "states": "SLEEPING"
      },
      "x_position": -1.7909343952709282,
      "y_position": -77.366191098499399
    },
    {
      "ID": 43,
      "direction": 4.4632556815270306,
      "state": {
        "states": "SEARCHING"
      },
      "x_position": 1114.209012870401,
      "y_position": 715.04854459388207
    },
    {
      "ID": 44,
      "direction": 8.8111435085027559,
      "state": {
        "states": "SEARCHING"
      },
      "x_position": -1270.4278555890278,
      "y_position": -1777.7978381360188
    },
    {
      "ID": 45,
      "direction": 14.782997864072222,
      "state": {
        "states": "SEARCHING"
      },
      "x_position": 1198.5477754944745,
      "y_position": 2921.1964102065131
    },
    {
      "ID": 46,
      "direction": 1.2009510988576131,
      "state": {
        "states": "SLEEPING"
      },
      "x_position": -67.438934428041264,
      "y_position": -177.3653269085853
    },
    {
      "ID": 47,
      "direction": 18.736144615824969,
      "state": {
        "states": "SEARCHING"
      },
      "x_position": 863.23424725921348,
      "y_position": -296.54285338230756
    },
    {
      "ID": 48,
      "direction": 7.6531086730516664,
      "state": {
        "states": "SEARCHING"
      },
      "x_position": -2966.8313674876449,
      "y_position": -3030.8070058294961
    },
    {
      "ID": 49,
      "direction": -1.5921197786511976,
      "state": {
        "states": "SEARCHING"
      },
      "x_position": -278.10189147992548,
      "y_position": -868.5931221100775
    },
    {
      "ID": 50,
      "direction": 0.78778723267639339,
      "state": {
        "states": "SEARCHING"
      },
      "x_position": -969.76809552313046,
      "y_position": -902.46152174042959
    },
    {
      "ID": 51,
      "direction": 6.7752501562812473,
      "state": {
        "states": "SLEEPING"
      },
      "x_position": -28.931991404474381,
      "y_position": -136.16602434643599
    },
    {
      "ID": 52,
      "direction": 1.0770122531803827,
      "state": {
        "states": "SEARCHING"
      },
      "x_position": -1107.1486953606793,
      "y_position": -433.72193335705828
    },
    {
      "ID": 53,
      "direction": -0.59672207773732933,
      "state": {
        "states": "SEARCHING"
      },
      "x_position": 187.9301649507654,
      "y_position": -356.99161217017553
    },
    {
      "ID": 54,
      "direction": 6.5014617444902401,
      "state": {
        "states": "SEARCHING"
      },
      "x_position": 1756.002302011068,
      "y_position": -1370.7811053624191
    },
    {
      "ID": 55,
      "direction": 7.800392408290751,
      "state": {
        "states": "SEARCHING"
      },
      "x_position": 1237.5939964811616,
      "y_position": -1182.2122364529098
    },
    {
      "ID": 56,
      "direction": 3.6645238440776691,
      "state": {
        "states": "SEARCHING"
      },
      "x_position": -574.67435369899874,
      "y_position": -1047.3747364019232
    },
    {
      "ID": 57,
      "direction": -13.55812238980948,
      "state": {
        "states": "SEARCHING"
      },
      "x_position": 1836.1470776480573,
      "y_position": 738.96876229553686
    },
    {
      "ID": 58,
      "direction": -19.614265958962093,
      "state": {
        "states": "SEARCHING"
      },
      "x_position": 294.20614693302264,
      "y_position": -503.15375951918264
    },
    {
      "ID": 59,
      "direction": 3.3533004062175631,
      "state": {
        "states": "SLEEPING"
      },
      "x_position": -108.61332387645984,
      "y_position": -48.113414014319609
    },
    {
      "ID": 60,
      "direction": 7.952461557992069,
      "state": {
        "states": "SEARCHING"
      },
      "x_position": -131.14428000340925,
      "y_position": -1783.5198372955024
    },
    {
      "ID": 61,
      "direction": 1.1763465736314584,
      "state": {
        "states": "SLEEPING"
      },
      "x_position": -63.275884520042574,
      "y_position": -104.28638536430428
    },
    {
      "ID": 62,
      "direction": -5.3524700882494605,
      "state": {
        "states": "SEARCHING"
      },
      "x_position": 341.02747836521809,
      "y_position": -1145.2570594931278
    },
    {
      "ID": 63,
      "direction": 13.808303648993034,
      "state": {
        "states": "SEARCHING"
      },
      "x_position": 1493.6953293309457,
      "y_position": 14.469071868531564
    },
    {
      "ID": 64,
      "direction": -1.2731824747329408,
      "state": {
        "states": "SEARCHING"
      },
      "x_position": -1845.507820521402,
      "y_position": -237.04259899187684
    },
    {
      "ID": 65,
      "direction": 2.3297140274674519,
      "state": {
        "states": "SLEEPING"
      },
      "x_position": 3.6275255494494796,
      "y_position": -33.201570029574668
    },
    {
      "ID": 66,
      "direction": -2.6297011712039779,
      "state": {
        "states": "SEARCHING"
      },
      "x_position": -520.9208034192643,
      "y_position": -824.8536017732182
    },
    {
      "ID": 67,
      "direction": 6.1486413286899158,
      "state": {
        "states": "SLEEPING"
      },
      "x_position": -12.257993592523162,
      "y_position": -166.2363327383982
    },
    {
      "ID": 68,
      "direction": 8.6109685334287622,
      "state": {
        "states": "SEARCHING"
      },
      "x_position": -1408.7796475917376,
      "y_position": 102.17065437011223
    },
    {
      "ID": 69,
      "direction": -4.3507028848657736,
      "state": {
        "states": "SEARCHING"
      },
      "x_position": 1374.5121018121326,
      "y_position": 41.408671689839842
    }
  ],
  "ticks": 111600
}